Metadata-Version: 2.1
Name: reapython
Version: 1.1.1
Summary: rea.py
Home-page: https://rea2.readthedocs.io/en/latest/
Author: robbeykaaso
Author-email: robbey_kaaso@sina.com
License: UNKNOWN
Platform: UNKNOWN
